RobotLog2RQM/CRQM.py
RobotLog2RQM/RobotLog2RQM.pdf
RobotLog2RQM/__init__.py
RobotLog2RQM/__main__.py
RobotLog2RQM/logger.py
RobotLog2RQM/robotlog2rqm.py
RobotLog2RQM/rqmtool.py
RobotLog2RQM/version.py
RobotLog2RQM/RQM_templates/buildrecord.xml
RobotLog2RQM/RQM_templates/configuration.xml
RobotLog2RQM/RQM_templates/executionresult.xml
RobotLog2RQM/RQM_templates/executionworkitem.xml
RobotLog2RQM/RQM_templates/suiteexecutionrecord.xml
RobotLog2RQM/RQM_templates/testcase.xml
RobotLog2RQM/RQM_templates/testsuite.xml
RobotLog2RQM/RQM_templates/testsuitelog.xml
robotframework_robotlog2rqm-1.7.0.dist-info/licenses/LICENSE
robotframework_robotlog2rqm-1.7.0.dist-info/METADATA
robotframework_robotlog2rqm-1.7.0.dist-info/WHEEL
robotframework_robotlog2rqm-1.7.0.dist-info/entry_points.txt
robotframework_robotlog2rqm-1.7.0.dist-info/top_level.txt
robotframework_robotlog2rqm-1.7.0.dist-info/RECORD
