Metadata-Version: 2.4
Name: robotframework-robotlog2rqm
Version: 1.7.0
Summary: Imports robot result(s) to IBM Rational Quality Manager (RQM)
Home-page: https://github.com/test-fullautomation/robotframework-robotlog2rqm
Author: Tran Duy Ngoan
Author-email: Ngoan.TranDuy@vn.bosch.com
Classifier: Programming Language :: Python :: 3
Classifier: License :: OSI Approved :: Apache Software License
Classifier: Operating System :: OS Independent
Classifier: Development Status :: 4 - Beta
Classifier: Intended Audience :: Developers
Classifier: Topic :: Software Development
Requires-Python: >=3.0
License-File: LICENSE
Requires-Dist: lxml
Requires-Dist: requests
Requires-Dist: colorama
Requires-Dist: robotframework
Dynamic: author
Dynamic: author-email
Dynamic: classifier
Dynamic: description
Dynamic: description-content-type
Dynamic: home-page
Dynamic: license-file
Dynamic: requires-dist
Dynamic: requires-python
Dynamic: summary
